[{"id":"xx-231244_436144","name":"Mosquée Barakat","lat":-23.124409,"lng":43.614397,"addr":"","type":"place_of_worship"},{"id":"xx-233479_436779","name":"Allah Mdoullilah","lat":-23.347938,"lng":43.677922,"addr":"","type":"place_of_worship"},{"id":"xx-233302_437019","name":"Islamic place","lat":-23.33021,"lng":43.701899,"addr":"","type":"place_of_worship"},{"id":"xx-217430_433613","name":"Mosquée Khoja","lat":-21.742999,"lng":43.361344,"addr":"","type":"place_of_worship"},{"id":"xx-217428_433642","name":"Mosque Aunnite","lat":-21.742783,"lng":43.364233,"addr":"","type":"place_of_worship"},{"id":"xx-216076_436753","name":"Mosquée Sunnite Ambahikily","lat":-21.607559,"lng":43.675293,"addr":"","type":"place_of_worship"},{"id":"xx-246916_447501","name":"Masjid Bilal","lat":-24.691638,"lng":44.750055,"addr":"","type":"place_of_worship"},{"id":"xx-233526_436672","name":"Islamic place","lat":-23.35259,"lng":43.667203,"addr":"","type":"yes"},{"id":"xx-233525_436651","name":"Dawoodi Bohra Masjid","lat":-23.352508,"lng":43.665123,"addr":"","type":"yes"},{"id":"xx-202924_442764","name":"Islamic place","lat":-20.292368,"lng":44.276365,"addr":"","type":"mosque"},{"id":"xx-202919_442739","name":"Islamic place","lat":-20.291851,"lng":44.273861,"addr":"","type":"mosque"},{"id":"xx-202921_443451","name":"Islamic place","lat":-20.292102,"lng":44.345078,"addr":"","type":"mosque"},{"id":"xx-217424_433641","name":"Mosquée Sunnite","lat":-21.742448,"lng":43.364065,"addr":"","type":"mosque"},{"id":"xx-217469_433636","name":"Islamic place","lat":-21.746921,"lng":43.363617,"addr":"","type":"mosque"},{"id":"xx-202921_443444","name":"Islamic place","lat":-20.292141,"lng":44.344414,"addr":"","type":"mosque"},{"id":"xx-202919_442738","name":"Islamic place","lat":-20.291882,"lng":44.273834,"addr":"","type":"mosque"},{"id":"xx-202922_443444","name":"Islamic place","lat":-20.292176,"lng":44.344405,"addr":"","type":"mosque"}]