[{"id":"xx408086_1116491","name":"清真大寺","lat":40.808568,"lng":111.649071,"addr":"","type":"place_of_worship"},{"id":"xx400915_1132933","name":"清真大寺","lat":40.091464,"lng":113.293323,"addr":"","type":"place_of_worship"},{"id":"xx408244_1148678","name":"新华街清真寺","lat":40.824411,"lng":114.867763,"addr":"","type":"yes"},{"id":"xx408168_1148683","name":"西关清真寺","lat":40.816847,"lng":114.868272,"addr":"","type":"yes"},{"id":"xx408136_1148899","name":"土尔沟清真寺","lat":40.813566,"lng":114.88989,"addr":"","type":"yes"},{"id":"xx408219_1148702","name":"清真女寺","lat":40.821939,"lng":114.870152,"addr":"","type":"yes"},{"id":"xx408160_1148743","name":"东关清真寺","lat":40.815974,"lng":114.874283,"addr":"","type":"yes"},{"id":"xx408085_1116491","name":"清真大寺","lat":40.808492,"lng":111.649059,"addr":"","type":"place_of_worship"},{"id":"xx400913_1132933","name":"清真大寺","lat":40.091345,"lng":113.29332,"addr":"","type":"place_of_worship"},{"id":"xx408219_1148701","name":"清真女寺","lat":40.821913,"lng":114.870142,"addr":"","type":"yes"},{"id":"xx408626_1131421","name":"礼拜寺清真寺","lat":40.862638,"lng":113.142115,"addr":"","type":"place_of_worship"},{"id":"xx412691_1134152","name":"二十号地清真寺","lat":41.269058,"lng":113.415197,"addr":"","type":"place_of_worship"},{"id":"xx408357_1148804","name":"上堡清真寺","lat":40.835749,"lng":114.880406,"addr":"","type":"yes"},{"id":"xx408093_1116426","name":"清真西寺","lat":40.809308,"lng":111.64261,"addr":"","type":"place_of_worship"},{"id":"xx408010_1116405","name":"清真南寺","lat":40.801039,"lng":111.640487,"addr":"","type":"yes"},{"id":"xx405954_1100243","name":"清真西寺","lat":40.595428,"lng":110.024251,"addr":"","type":"place_of_worship"},{"id":"xx405935_1100328","name":"清真大寺","lat":40.593528,"lng":110.032767,"addr":"","type":"place_of_worship"},{"id":"xx405913_1100224","name":"清真中寺","lat":40.591318,"lng":110.022379,"addr":"","type":"place_of_worship"},{"id":"xx408010_1116404","name":"清真南寺","lat":40.801006,"lng":111.640439,"addr":"","type":"yes"},{"id":"xx405954_1100241","name":"清真西寺","lat":40.595423,"lng":110.024097,"addr":"","type":"place_of_worship"},{"id":"xx405934_1100328","name":"清真大寺","lat":40.593406,"lng":110.03276,"addr":"","type":"place_of_worship"},{"id":"xx405913_1100223","name":"清真中寺","lat":40.591312,"lng":110.022306,"addr":"","type":"place_of_worship"},{"id":"xx405968_1100277","name":"瓦窑沟清真寺","lat":40.59684,"lng":110.02771,"addr":"","type":"place_of_worship"},{"id":"xx408034_1116351","name":"祥和清真寺","lat":40.803365,"lng":111.635122,"addr":"","type":"yes"},{"id":"xx408383_1117215","name":"团结清真寺","lat":40.838315,"lng":111.721537,"addr":"","type":"yes"},{"id":"xx410812_1114543","name":"武川清真寺","lat":41.08119,"lng":111.454302,"addr":"","type":"yes"},{"id":"xx417064_1104401","name":"百灵庙清真寺","lat":41.706443,"lng":110.44015,"addr":"","type":"mosque"},{"id":"xx410385_1100584","name":"固阳县清真寺","lat":41.038477,"lng":110.058415,"addr":"","type":"yes"}]